injectq/__init__.py
injectq/py.typed
injectq/components/__init__.py
injectq/core/__init__.py
injectq/core/async_scopes.py
injectq/core/base_scope_manager.py
injectq/core/container.py
injectq/core/context.py
injectq/core/registry.py
injectq/core/resolver.py
injectq/core/scopes.py
injectq/core/thread_safe_resolver.py
injectq/core/thread_safety.py
injectq/decorators/__init__.py
injectq/decorators/inject.py
injectq/decorators/resource.py
injectq/decorators/singleton.py
injectq/diagnostics/__init__.py
injectq/diagnostics/profiling.py
injectq/diagnostics/validation.py
injectq/diagnostics/visualization.py
injectq/integrations/__init__.py
injectq/integrations/fastapi.py
injectq/integrations/taskiq.py
injectq/modules/__init__.py
injectq/modules/base.py
injectq/testing/__init__.py
injectq/testing/utilities.py
injectq/utils/__init__.py
injectq/utils/exceptions.py
injectq/utils/helpers.py
injectq/utils/protocols.py
injectq/utils/types.py
injectq-0.3.4.dist-info/METADATA
injectq-0.3.4.dist-info/WHEEL
injectq-0.3.4.dist-info/licenses/LICENSE
injectq-0.3.4.dist-info/RECORD
