Metadata-Version: 2.4
Name: injectq
Version: 0.3.4
Summary: Modern Python dependency injection library combining simplicity, power, and performance
Project-URL: Homepage, https://github.com/Iamsdt/injectq
Project-URL: Documentation, https://github.com/Iamsdt/injectq
Project-URL: Repository, https://github.com/Iamsdt/injectq
Project-URL: Issues, https://github.com/Iamsdt/injectq/issues
Author: InjectQ Contributors
License-Expression: MIT
License-File: LICENSE
Keywords: container,dependency-injection,di,inversion-of-control,ioc
Classifier: Development Status :: 4 - Beta
Classifier: Intended Audience :: Developers
Classifier: License :: OSI Approved :: MIT License
Classifier: Operating System :: OS Independent
Classifier: Programming Language :: Python :: 3
Classifier: Programming Language :: Python :: 3.10
Classifier: Programming Language :: Python :: 3.11
Classifier: Programming Language :: Python :: 3.12
Classifier: Programming Language :: Python :: 3.13
Classifier: Topic :: Software Development :: Libraries
Classifier: Topic :: Software Development :: Libraries :: Python Modules
Classifier: Typing :: Typed
Requires-Python: >=3.10
Requires-Dist: typing-extensions>=4.0.0
Provides-Extra: dev
Requires-Dist: black>=22.0.0; extra == 'dev'
Requires-Dist: fastapi>=0.68.0; extra == 'dev'
Requires-Dist: flake8>=4.0.0; extra == 'dev'
Requires-Dist: httpx>=0.28.1; extra == 'dev'
Requires-Dist: isort>=5.0.0; extra == 'dev'
Requires-Dist: mypy>=1.0.0; extra == 'dev'
Requires-Dist: pytest-asyncio>=0.21.0; extra == 'dev'
Requires-Dist: pytest-cov>=3.0.0; extra == 'dev'
Requires-Dist: pytest>=6.0.0; extra == 'dev'
Requires-Dist: taskiq>=0.11.18; extra == 'dev'
Provides-Extra: fastapi
Requires-Dist: fastapi>=0.68.0; extra == 'fastapi'
Provides-Extra: taskiq
Requires-Dist: taskiq>=0.9.0; extra == 'taskiq'
Provides-Extra: testing
Requires-Dist: pytest-asyncio>=0.21.0; extra == 'testing'
Requires-Dist: pytest>=6.0.0; extra == 'testing'
